odoo/addons/ssi_non_assurance_report_state_change_constrain/README.rst
odoo/addons/ssi_non_assurance_report_state_change_constrain/__init__.py
odoo/addons/ssi_non_assurance_report_state_change_constrain/__manifest__.py
odoo/addons/ssi_non_assurance_report_state_change_constrain/models/__init__.py
odoo/addons/ssi_non_assurance_report_state_change_constrain/models/accountant_non_assurance_report.py
odoo/addons/ssi_non_assurance_report_state_change_constrain/static/description/icon.png
odoo14_addon_ssi_non_assurance_report_state_change_constrain-14.0.1.3.0.dist-info/METADATA
odoo14_addon_ssi_non_assurance_report_state_change_constrain-14.0.1.3.0.dist-info/WHEEL
odoo14_addon_ssi_non_assurance_report_state_change_constrain-14.0.1.3.0.dist-info/top_level.txt
odoo14_addon_ssi_non_assurance_report_state_change_constrain-14.0.1.3.0.dist-info/RECORD
